vineyard/drivers/migrate/__init__.py
vineyard/drivers/migrate/__main__.py
vineyard/drivers/migrate/_program.py
vineyard/drivers/migrate/local/__init__.py
vineyard/drivers/migrate/local/__main__.py
vineyard/drivers/migrate/stream/__init__.py
vineyard/drivers/migrate/stream/__main__.py
vineyard/drivers/migrate/tools/__init__.py
vineyard/drivers/migrate/tools/vineyard-migrate
vineyard/drivers/migrate/tools/vineyard-migrate-stream
vineyard/drivers/migrate/tools/vineyard-migrate-to-local
vineyard_migrate-0.7.1.dist-info/LICENSE
vineyard_migrate-0.7.1.dist-info/METADATA
vineyard_migrate-0.7.1.dist-info/NOTICE.txt
vineyard_migrate-0.7.1.dist-info/WHEEL
vineyard_migrate-0.7.1.dist-info/entry_points.txt
vineyard_migrate-0.7.1.dist-info/top_level.txt
vineyard_migrate-0.7.1.dist-info/RECORD
